MANIFEST.in
setup.py
automatabpp/__init__.py
automatabpp/automatabpp.py
automatabpp.egg-info/PKG-INFO
automatabpp.egg-info/SOURCES.txt
automatabpp.egg-info/dependency_links.txt
automatabpp.egg-info/top_level.txt
automatabpp/commandqueue/__init__.py
automatabpp/commandqueue/commandqueue.py
automatabpp/comparisons/__init__.py
automatabpp/comparisons/comparisons.py
automatabpp/constants/__init__.py
automatabpp/machine/__init__.py
automatabpp/machine/machine.py
automatabpp/machines/__init__.py
automatabpp/machines/machines.py
automatabpp/metaclasses/__init__.py
automatabpp/metaclasses/singleton.py
automatabpp/state/__init__.py
automatabpp/state/state.py
automatabpp/xml/__init__.py
automatabpp/xml/xmlread.py